{"frames":{"015":{"frame":{"x":1,"y":1,"w":412,"h":329},"sourceSize":{"w":412,"h":329}},"000":{"frame":{"x":415,"y":1,"w":308,"h":232},"sourceSize":{"w":308,"h":232}},"german_dog_head":{"frame":{"x":415,"y":235,"w":90,"h":91},"sourceSize":{"w":90,"h":91}},"german_couplle_tape4":{"frame":{"x":507,"y":235,"w":19,"h":89},"sourceSize":{"w":19,"h":89}},"german_couplle_girl_body":{"frame":{"x":528,"y":235,"w":53,"h":88},"sourceSize":{"w":53,"h":88}},"german_couplle_tape1":{"frame":{"x":583,"y":235,"w":27,"h":87},"sourceSize":{"w":27,"h":87}},"german_couplle_boy_leg2":{"frame":{"x":612,"y":235,"w":41,"h":84},"sourceSize":{"w":41,"h":84}},"german_couplle_tape3":{"frame":{"x":655,"y":235,"w":24,"h":82},"sourceSize":{"w":24,"h":82}},"Bitmap 3":{"frame":{"x":655,"y":319,"w":4,"h":11},"sourceSize":{"w":4,"h":11}},"Bitmap 1":{"frame":{"x":661,"y":319,"w":4,"h":11},"sourceSize":{"w":4,"h":11}},"german_couplle_tape9":{"frame":{"x":681,"y":235,"w":21,"h":79},"sourceSize":{"w":21,"h":79}},"Bitmap 7":{"frame":{"x":681,"y":316,"w":16,"h":14},"sourceSize":{"w":16,"h":14}},"german_couplle_tape16":{"frame":{"x":704,"y":235,"w":15,"h":73},"sourceSize":{"w":15,"h":73}},"Bitmap 4":{"frame":{"x":704,"y":310,"w":13,"h":20},"sourceSize":{"w":13,"h":20}},"014":{"frame":{"x":725,"y":1,"w":236,"h":304},"sourceSize":{"w":236,"h":304}},"german_couplle_girl_hand_2":{"frame":{"x":725,"y":307,"w":60,"h":20},"sourceSize":{"w":60,"h":20}},"german_couplle_girl_hand_1":{"frame":{"x":787,"y":307,"w":48,"h":17},"sourceSize":{"w":48,"h":17}},"german_couplle_boy_hand2":{"frame":{"x":837,"y":307,"w":44,"h":19},"sourceSize":{"w":44,"h":19}},"german_couplle_girl_skirt4":{"frame":{"x":883,"y":307,"w":40,"h":11},"sourceSize":{"w":40,"h":11}},"german_couplle_boy_foot3":{"frame":{"x":925,"y":307,"w":27,"h":18},"sourceSize":{"w":27,"h":18}},"german_couplle_girl_skirt7":{"frame":{"x":963,"y":1,"w":39,"h":176},"sourceSize":{"w":39,"h":176}},"italy_rope":{"frame":{"x":1004,"y":1,"w":10,"h":105},"sourceSize":{"w":10,"h":105}},"german_couplle_tape17":{"frame":{"x":1004,"y":108,"w":18,"h":67},"sourceSize":{"w":18,"h":67}},"german_couplle_tape19":{"frame":{"x":963,"y":179,"w":44,"h":123},"sourceSize":{"w":44,"h":123}},"german_couplle_tape7":{"frame":{"x":1009,"y":179,"w":14,"h":60},"sourceSize":{"w":14,"h":60}},"german_couplle_tape6":{"frame":{"x":1009,"y":241,"w":14,"h":55},"sourceSize":{"w":14,"h":55}},"german_couplle_girl_fist_1":{"frame":{"x":963,"y":304,"w":27,"h":22},"sourceSize":{"w":27,"h":22}},"010":{"frame":{"x":992,"y":304,"w":25,"h":22},"sourceSize":{"w":25,"h":22}},"german_couplle_girl_skirt8":{"frame":{"x":1,"y":332,"w":62,"h":183},"sourceSize":{"w":62,"h":183}},"german_couplle_girl_skirt2":{"frame":{"x":1,"y":517,"w":62,"h":176},"sourceSize":{"w":62,"h":176}},"german_couplle_girl_skirt5":{"frame":{"x":1,"y":695,"w":58,"h":165},"sourceSize":{"w":58,"h":165}},"german_couplle_girl_skirt1":{"frame":{"x":1,"y":862,"w":43,"h":161},"sourceSize":{"w":43,"h":161}},"german_couplle_tape15":{"frame":{"x":46,"y":862,"w":17,"h":63},"sourceSize":{"w":17,"h":63}},"Bitmap 2":{"frame":{"x":46,"y":927,"w":13,"h":20},"sourceSize":{"w":13,"h":20}},"german_dog_pupil":{"frame":{"x":46,"y":949,"w":12,"h":12},"sourceSize":{"w":12,"h":12}},"german_couplle_girl_skirt6":{"frame":{"x":65,"y":332,"w":73,"h":173},"sourceSize":{"w":73,"h":173}},"german_couplle_girl_skirt3":{"frame":{"x":65,"y":507,"w":43,"h":163},"sourceSize":{"w":43,"h":163}},"german_couplle_tape2":{"frame":{"x":110,"y":507,"w":21,"h":97},"sourceSize":{"w":21,"h":97}},"german_couplle_tape13":{"frame":{"x":110,"y":606,"w":20,"h":64},"sourceSize":{"w":20,"h":64}},"german_dog_tail":{"frame":{"x":65,"y":672,"w":64,"h":120},"sourceSize":{"w":64,"h":120}},"german_couplle_tape5":{"frame":{"x":65,"y":794,"w":33,"h":100},"sourceSize":{"w":33,"h":100}},"german_couplle_tape18":{"frame":{"x":100,"y":794,"w":24,"h":79},"sourceSize":{"w":24,"h":79}},"german_couplle_boy_arm1":{"frame":{"x":65,"y":896,"w":51,"h":78},"sourceSize":{"w":51,"h":78}},"german_couplle_tape8":{"frame":{"x":118,"y":896,"w":20,"h":57},"sourceSize":{"w":20,"h":57}},"007":{"frame":{"x":65,"y":976,"w":65,"h":44},"sourceSize":{"w":65,"h":44}},"001":{"frame":{"x":140,"y":332,"w":133,"h":170},"sourceSize":{"w":133,"h":170}},"german_house_mask":{"frame":{"x":140,"y":504,"w":102,"h":167},"sourceSize":{"w":102,"h":167}},"005":{"frame":{"x":244,"y":504,"w":27,"h":70},"sourceSize":{"w":27,"h":70}},"german_couplle_tape10":{"frame":{"x":244,"y":576,"w":21,"h":69},"sourceSize":{"w":21,"h":69}},"german_dog_tongue":{"frame":{"x":244,"y":647,"w":19,"h":23},"sourceSize":{"w":19,"h":23}},"german_couplle_boy_body":{"frame":{"x":140,"y":673,"w":89,"h":103},"sourceSize":{"w":89,"h":103}},"german_couplle_boy_leg1":{"frame":{"x":231,"y":673,"w":34,"h":78},"sourceSize":{"w":34,"h":78}},"german_couplle_boy_foot2":{"frame":{"x":231,"y":753,"w":21,"h":23},"sourceSize":{"w":21,"h":23}},"german_dog_neck":{"frame":{"x":140,"y":778,"w":83,"h":51},"sourceSize":{"w":83,"h":51}},"german_dog_ear1":{"frame":{"x":225,"y":778,"w":28,"h":49},"sourceSize":{"w":28,"h":49}},"german_couplle_girl_arm_1":{"frame":{"x":255,"y":778,"w":18,"h":33},"sourceSize":{"w":18,"h":33}},"003":{"frame":{"x":140,"y":831,"w":79,"h":60},"sourceSize":{"w":79,"h":60}},"german_green_flag2":{"frame":{"x":221,"y":831,"w":30,"h":60},"sourceSize":{"w":30,"h":60}},"german_couplle_tape12":{"frame":{"x":253,"y":831,"w":20,"h":54},"sourceSize":{"w":20,"h":54}},"german_couplle_boy_hip1":{"frame":{"x":140,"y":893,"w":58,"h":73},"sourceSize":{"w":58,"h":73}},"german_couplle_girl_arm_2":{"frame":{"x":140,"y":968,"w":22,"h":55},"sourceSize":{"w":22,"h":55}},"004":{"frame":{"x":164,"y":968,"w":33,"h":53},"sourceSize":{"w":33,"h":53}},"german_couplle_boy_hip2":{"frame":{"x":200,"y":893,"w":43,"h":69},"sourceSize":{"w":43,"h":69}},"german_couplle_tape14":{"frame":{"x":245,"y":893,"w":27,"h":66},"sourceSize":{"w":27,"h":66}},"german_couplle_boy_arm2":{"frame":{"x":200,"y":964,"w":62,"h":36},"sourceSize":{"w":62,"h":36}},"011":{"frame":{"x":200,"y":1002,"w":21,"h":21},"sourceSize":{"w":21,"h":21}},"002":{"frame":{"x":275,"y":332,"w":153,"h":164},"sourceSize":{"w":153,"h":164}},"german_couplle_tape11":{"frame":{"x":275,"y":498,"w":30,"h":68},"sourceSize":{"w":30,"h":68}},"german_yellow_flag2":{"frame":{"x":307,"y":498,"w":36,"h":68},"sourceSize":{"w":36,"h":68}},"german_couplle_girl_hair":{"frame":{"x":345,"y":498,"w":49,"h":67},"sourceSize":{"w":49,"h":67}},"german_blue_flag_2":{"frame":{"x":396,"y":498,"w":32,"h":57},"sourceSize":{"w":32,"h":57}},"german_couplle_boy_head":{"frame":{"x":275,"y":568,"w":62,"h":66},"sourceSize":{"w":62,"h":66}},"german_couplle_boy_ess":{"frame":{"x":339,"y":568,"w":61,"h":42},"sourceSize":{"w":61,"h":42}},"german_couplle_boy_hip4":{"frame":{"x":402,"y":568,"w":26,"h":44},"sourceSize":{"w":26,"h":44}},"bird_body1":{"frame":{"x":275,"y":636,"w":54,"h":61},"sourceSize":{"w":54,"h":61}},"german_couplle_girl_head":{"frame":{"x":331,"y":636,"w":56,"h":58},"sourceSize":{"w":56,"h":58}},"008":{"frame":{"x":389,"y":636,"w":38,"h":57},"sourceSize":{"w":38,"h":57}},"german_red_flag2":{"frame":{"x":275,"y":699,"w":42,"h":56},"sourceSize":{"w":42,"h":56}},"german_violet_flag2":{"frame":{"x":319,"y":699,"w":34,"h":52},"sourceSize":{"w":34,"h":52}},"bird_body2":{"frame":{"x":355,"y":699,"w":50,"h":42},"sourceSize":{"w":50,"h":42}},"german_couplle_boy_hand1":{"frame":{"x":407,"y":699,"w":20,"h":35},"sourceSize":{"w":20,"h":35}},"009":{"frame":{"x":275,"y":757,"w":47,"h":35},"sourceSize":{"w":47,"h":35}},"german_couplle_girl_sleeve2":{"frame":{"x":324,"y":757,"w":39,"h":34},"sourceSize":{"w":39,"h":34}},"german_blue_flag":{"frame":{"x":365,"y":757,"w":37,"h":34},"sourceSize":{"w":37,"h":34}},"006":{"frame":{"x":404,"y":757,"w":24,"h":32},"sourceSize":{"w":24,"h":32}},"german_couplle_boy_hip3":{"frame":{"x":275,"y":794,"w":30,"h":47},"sourceSize":{"w":30,"h":47}},"german_couplle_girl_sleeve1":{"frame":{"x":307,"y":794,"w":44,"h":46},"sourceSize":{"w":44,"h":46}},"german_green_flag":{"frame":{"x":353,"y":794,"w":46,"h":41},"sourceSize":{"w":46,"h":41}},"german_dog_ear2":{"frame":{"x":401,"y":794,"w":27,"h":45},"sourceSize":{"w":27,"h":45}},"german_couplle_boy_foot1":{"frame":{"x":275,"y":843,"w":29,"h":43},"sourceSize":{"w":29,"h":43}},"german_violet_flag":{"frame":{"x":306,"y":843,"w":39,"h":41},"sourceSize":{"w":39,"h":41}},"013":{"frame":{"x":347,"y":843,"w":39,"h":36},"sourceSize":{"w":39,"h":36}},"german_red_flag":{"frame":{"x":388,"y":843,"w":39,"h":38},"sourceSize":{"w":39,"h":38}},"german_yellow_flag":{"frame":{"x":275,"y":888,"w":38,"h":36},"sourceSize":{"w":38,"h":36}},"german_couplle_fists":{"frame":{"x":275,"y":926,"w":37,"h":36},"sourceSize":{"w":37,"h":36}},"012":{"frame":{"x":275,"y":964,"w":33,"h":35},"sourceSize":{"w":33,"h":35}},"german_dog_nose":{"frame":{"x":315,"y":888,"w":35,"h":30},"sourceSize":{"w":35,"h":30}},"bird_head1":{"frame":{"x":315,"y":920,"w":33,"h":34},"sourceSize":{"w":33,"h":34}},"bird_head2":{"frame":{"x":315,"y":956,"w":32,"h":33},"sourceSize":{"w":32,"h":33}}},"meta":{"app":"PixiAnimate","scale":1,"image":"germany_atlas_1.png","size":{"w":1024,"h":1024}}}